pydicts/__init__.py
pydicts/casts.py
pydicts/classes.py
pydicts/colors.py
pydicts/currencies.json
pydicts/currency.py
pydicts/dod.py
pydicts/exceptions.py
pydicts/locale/en/LC_MESSAGES/pydicts.mo
pydicts/locale/en.po
pydicts/locale/es/LC_MESSAGES/pydicts.mo
pydicts/locale/es.po
pydicts/locale/pydicts.pot
pydicts/lod.py
pydicts/lod_xyv.py
pydicts/lod_ymv.py
pydicts/lol.py
pydicts/myjsonencoder.py
pydicts/percentage.py
pydicts/poethepoet.py
pydicts/pylatex.py
pydicts/tests/__init__.py
pydicts/tests/test_casts.py
pydicts/tests/test_colors.py
pydicts/tests/test_currency.py
pydicts/tests/test_dod.py
pydicts/tests/test_lod.py
pydicts/tests/test_lod_ymv.py
pydicts/tests/test_lol.py
pydicts/tests/test_myjsonencoder.py
pydicts/tests/test_percentage.py
pydicts/tests/test_pylatex.py
pydicts-1.1.0.dist-info/LICENSE
pydicts-1.1.0.dist-info/METADATA
pydicts-1.1.0.dist-info/WHEEL
pydicts-1.1.0.dist-info/RECORD
