Metadata-Version: 2.3
Name: pydicts
Version: 1.1.0
Summary: Module to use dictionaries in various situations
License: GPL-3.0-only
Author: turulomio
Author-email: turulomio@yahoo.es
Requires-Python: >=3.9,<4
Classifier: License :: OSI Approved :: GNU General Public License v3 (GPLv3)
Classifier: Programming Language :: Python :: 3
Classifier: Programming Language :: Python :: 3.9
Classifier: Programming Language :: Python :: 3.10
Classifier: Programming Language :: Python :: 3.11
Classifier: Programming Language :: Python :: 3.12
Classifier: Programming Language :: Python :: 3.13
Provides-Extra: latex
Requires-Dist: colorama (>=0.4.6)
Requires-Dist: isodate (>=0.7.2)
Requires-Dist: pylatex (>=1.4.2,<2.0.0) ; extra == "latex"
Requires-Dist: tabulate (>=0.9.0)
Project-URL: Homepage, https://github.com/turulomio/pydicts/
Project-URL: Repository, https://github.com/turulomio/pydicts/
Project-URL: changelog, https://github.com/turulomio/pydicts#changelog
